.editorconfig
.gitignore
.readthedocs.yml
.travis.yml
AUTHORS.rst
CONTRIBUTING.rst
HISTORY.rst
LICENSE
MANIFEST.in
Makefile
README.rst
paper.bib
paper.md
requirements.txt
setup.cfg
setup.py
.github/ISSUE_TEMPLATE.md
docs/Makefile
docs/source/background.rst
docs/source/conf.py
docs/source/gffpandas.py
docs/source/gffpandas.rst
docs/source/index.rst
docs/source/installation.rst
docs/source/introduction.rst
docs/source/logo_latest.png
docs/source/tutorial.rst
gffpandas/__init__.py
gffpandas/gffpandas.py
gffpandas_jb.egg-info/PKG-INFO
gffpandas_jb.egg-info/SOURCES.txt
gffpandas_jb.egg-info/dependency_links.txt
gffpandas_jb.egg-info/not-zip-safe
gffpandas_jb.egg-info/requires.txt
gffpandas_jb.egg-info/top_level.txt
tests/__init__.py
tests/test_gffpandas.py
tests/testdata/test_file.gff