Metadata-Version: 1.2
Name: gffpandas-jb
Version: 1.2.1.1
Summary: GFF annotations in panda data frames
Home-page: https://github.com/foerstner-lab/gffpandas
Author: Muhammad M. Elhossary, Vivian A. Monzon, Konrad U. Förstner
Author-email: elhossary@zbmed.de, vivian.monzon@stud-mail.uni-wuerzburg.de, konrad@foerstner.org
Maintainer-email: joel@generisbio.com
License: ISC license
Keywords: gffpandas
Platform: UNKNOWN
Classifier: Development Status :: 4 - Beta
Classifier: Intended Audience :: Developers
Classifier: License :: OSI Approved :: ISC License (ISCL)
Classifier: Natural Language :: English
Classifier: Programming Language :: Python :: 3
